software_metrics_machine/__init__.py
software_metrics_machine/apps/__init__.py
software_metrics_machine/apps/cli/__init__.py
software_metrics_machine/apps/cli/codemaat_fetch.py
software_metrics_machine/apps/cli/github_fetch_jobs_pipeline.py
software_metrics_machine/apps/cli/github_fetch_pipeline.py
software_metrics_machine/apps/cli/github_fetch_prs.py
software_metrics_machine/apps/cli/github_fetch_prs_comments.py
software_metrics_machine/apps/cli/pipeline_by_status.py
software_metrics_machine/apps/cli/pipeline_deployment_frequency.py
software_metrics_machine/apps/cli/pipeline_jobs_by_status.py
software_metrics_machine/apps/cli/pipeline_jobs_summary.py
software_metrics_machine/apps/cli/pipeline_jobs_time_execution.py
software_metrics_machine/apps/cli/pipeline_lead_time.py
software_metrics_machine/apps/cli/pipeline_runs_by.py
software_metrics_machine/apps/cli/pipeline_runs_duration.py
software_metrics_machine/apps/cli/pipeline_summary.py
software_metrics_machine/apps/cli/pull_request_average_of_comments_by_prs.py
software_metrics_machine/apps/cli/pull_request_average_of_prs_open_by.py
software_metrics_machine/apps/cli/pull_request_through_time.py
software_metrics_machine/apps/cli/pull_request_view_average_review_time_by_author.py
software_metrics_machine/apps/cli/pull_request_view_prs_by_author.py
software_metrics_machine/apps/cli/pull_request_view_summary.py
software_metrics_machine/apps/cli/pydriller_change_set.py
software_metrics_machine/apps/cli/source_code_code_churn.py
software_metrics_machine/apps/cli/source_code_coupling.py
software_metrics_machine/apps/cli/source_code_entity_churn.py
software_metrics_machine/apps/cli/source_code_entity_effort.py
software_metrics_machine/apps/cli/source_code_entity_ownership.py
software_metrics_machine/apps/cli/source_code_metadata.py
software_metrics_machine/apps/cli/source_code_pairing_index.py
software_metrics_machine/apps/cli/tools_json_file_merger.py
software_metrics_machine/apps/components/__init__.py
software_metrics_machine-0.2.0.dist-info/METADATA
software_metrics_machine-0.2.0.dist-info/WHEEL
software_metrics_machine-0.2.0.dist-info/entry_points.txt
software_metrics_machine-0.2.0.dist-info/RECORD
