Metadata-Version: 2.4
Name: software-metrics-machine
Version: 0.2.0
Summary: A data-driven approach to software measurament for high-performing teams
Requires-Python: >=3.14,<4.0
Classifier: Programming Language :: Python :: 3
Classifier: Programming Language :: Python :: 3.14
Requires-Dist: click (>=8.3.0,<9.0.0)
Requires-Dist: fastapi[standard] (>=0.117.1,<0.118.0)
Requires-Dist: holoviews (>=1.21.0,<2.0.0)
Requires-Dist: langchain (>=0.3.27,<0.4.0)
Requires-Dist: langchain-community (>=0.3.31,<0.4.0)
Requires-Dist: networkx (>=3.5,<4.0)
Requires-Dist: ollama (>=0.6.0,<0.7.0)
Requires-Dist: pandas (>=2.3.2,<3.0.0)
Requires-Dist: panel (>=1.8.0,<2.0.0)
Requires-Dist: pydantic (>=2.12.5,<3.0.0)
Requires-Dist: pydriller (>=2.9,<3.0)
Requires-Dist: requests (>=2.32.5,<3.0.0)
Requires-Dist: rich (>=14.2.0,<15.0.0)
Requires-Dist: squarify (>=0.4.4,<0.5.0)
Project-URL: Homepage, https://marabesi.github.io/software-metrics-machine
Project-URL: Issues, https://github.com/marabesi/software-metrics-machine/issues
